[{"p":496,"w":"حٰمٓ/حمٓ/./ha-meem","e":"Ha Meem","m":"হা-মীম","fm":"হা-মীম।","fme":"Ha-Mim. [These letters are one of the miracles of the Quran and none but Allah (Alone) knows their meanings"},{"p":496,"w":"وَالْكِتٰبِ/وَٱلۡكِتَٰبِ/./wal-kitabi|الْمُبِیْنِ/ٱلۡمُبِينِ/./al-mubini","e":"By the Book//the clear","m":"শপথ (এই) কিতাবের//সুস্পষ্ট","fm":"শপথ সুস্পষ্ট কিতাবের।","fme":"By the manifest Book (this Quran) that makes things clear"},{"p":496,"w":"اِنَّاۤ/إِنَّآ/./inna|اَنْزَلْنٰهُ/أَنزَلۡنَٰهُ/./anzalnahu|فِیْ/فِي/./fi|لَیْلَةٍ/لَيۡلَةٖ/./laylatin|مُّبٰرَكَةٍ/مُّبَٰرَكَةٍۚ/./mubarakatin|اِنَّا/إِنَّا/./inna|كُنَّا/كُنَّا/./kunna|مُنْذِرِیْنَ/مُنذِرِينَ/./mundhirina","e":"Indeed We//revealed it//in//a Night//Blessed//Indeed We//[We] are//(ever) warning","m":"নিশ্চয়ই আমরা//তা আমরা অবতীর্ণ করেছি//মধ্যে//এক রাতের//সৌভাগ্যময়//নিশ্চয়ই আমরা//আমরা ছিলাম//সতর্ককারী","fm":"আমি একে নাযিল করেছি। এক বরকতময় রাতে, নিশ্চয় আমি সতর্ককারী।","fme":"We sent it (this Quran) down on a blessed night [(i.e. night of Qadr, Surah No: 97) in the month of Ramadan,, the 9th month of the Islamic calendar]. Verily, We are ever warning [mankind that Our Torment will reach those who disbelieve in Our Oneness of Lordship and in Our Oneness of worship]"},{"p":496,"w":"فِیْهَا/فِيهَا/./fiha|یُفْرَقُ/يُفۡرَقُ/./yuf'raqu|كُلُّ/كُلُّ/./kullu|اَمْرٍ/أَمۡرٍ/./amrin|حَكِیْمٍ/حَكِيمٍ/./hakimin","e":"Therein//is made distinct//every//affair//wise","m":"তার মধ্যে(অর্থাৎ সেই রাতে)//স্থির করা হয়//প্রত্যেক//বিষয়//বিজ্ঞতাপূর্ণ","fm":"এ রাতে প্রত্যেক প্রজ্ঞাপূর্ণ বিষয় স্থিরীকৃত হয়।","fme":"Therein (that night) is decreed every matter of ordainments"},{"p":496,"w":"اَمْرًا/أَمۡرٗا/./amran|مِّنْ/مِّنۡ/./min|عِنْدِنَا ؕ—/عِندِنَآۚ/./indina|اِنَّا/إِنَّا/./inna|كُنَّا/كُنَّا/./kunna|مُرْسِلِیْنَ/مُرۡسِلِينَ/./mur'silina","e":"A command//from//Us//Indeed We//[We] are//(ever) sending","m":"নির্দেশক্রমে//থেকে//আমাদের নিকট//নিশ্চয়ই আমরা//আমরা ছিলাম//(এক রাসূল) প্রেরণকারী","fm":"আমার পক্ষ থেকে আদেশক্রমে, আমিই প্রেরণকারী।","fme":"Amran (i.e. a Command or this Quran or the Decree of every matter) from Us. Verily, We are ever sending (the Messengers)"},{"p":496,"w":"رَحْمَةً/رَحۡمَةٗ/./rahmatan|مِّنْ/مِّن/./min|رَّبِّكَ ؕ—/رَّبِّكَۚ/./rabbika|اِنَّهٗ/إِنَّهُۥ/./innahu|هُوَ/هُوَ/./huwa|السَّمِیْعُ/ٱلسَّمِيعُ/./al-sami'u|الْعَلِیْمُ/ٱلۡعَلِيمُ/./al-'alimu","e":"As Mercy//from//your Lord//Indeed He//[He]//(is) the AllHearer//the AllKnower","m":"অনুগ্রহস্বরূপ//পক্ষ হ'তে//তোমার রবের//নিশ্চয়ই তিনি//তিনিই//সব কিছুই শুনেন//সবকিছু জানেন","fm":"আপনার পালনকর্তার পক্ষ থেকে রহমতস্বরূপ। তিনি সর্বশ্রোতা, সর্বজ্ঞ।","fme":"(As) a Mercy from your Lord. Verily! He is the All-Hearer, the All-Knower"},{"p":496,"w":"رَبِّ/رَبِّ/./rabbi|السَّمٰوٰتِ/ٱلسَّمَٰوَٰتِ/./al-samawati|وَالْاَرْضِ/وَٱلۡأَرۡضِ/./wal-ardi|وَمَا/وَمَا/./wama|بَیْنَهُمَا ۘ—/بَيۡنَهُمَآۖ/./baynahuma|اِنْ/إِن/./in|كُنْتُمْ/كُنتُم/./kuntum|مُّوْقِنِیْنَ/مُّوقِنِينَ/./muqinina","e":"Lord//(of) the heavens//and the earth//and whatever//(is) between both of them//if//you are//certain","m":"(তিনি) রব//আকাশের//ও পৃথিবীর//এবং যা কিছু//উভয়ের মাঝে আছে//যদি//তোমরা হয়ে থাকো//নিশ্চিত বিশ্বাসী","fm":"যদি তোমাদের বিশ্বাস থাকে দেখতে পাবে। তিনি নভোমন্ডল, ভূমন্ডল ও এতদুভয়ের মধ্যেবর্তী সবকিছুর পালনকর্তা।","fme":"The Lord of the heavens and the earth and all that is between them, if you (but) have a faith with certainty"},{"p":496,"w":"لَاۤ/لَآ/./la|اِلٰهَ/إِلَٰهَ/./ilaha|اِلَّا/إِلَّا/./illa|هُوَ/هُوَ/./huwa|یُحْیٖ/يُحۡيِۦ/./yuh'yi|وَیُمِیْتُ ؕ—/وَيُمِيتُۖ/./wayumitu|رَبُّكُمْ/رَبُّكُمۡ/./rabbukum|وَرَبُّ/وَرَبُّ/./warabbu|اٰبَآىِٕكُمُ/ءَابَآئِكُمُ/./abaikumu|الْاَوَّلِیْنَ/ٱلۡأَوَّلِينَ/./al-awalina","e":"(There is) no//god//except//Him//He gives life//and causes death//your Lord//and (the) Lord//(of) your fathers//the former","m":"নেই//কোনো ইলাহ//ছাড়া//তিনি//তিনি জীবন দেন//এবং মৃত্যুও ঘটান//তোমাদের রব//ও রব//তোমাদের পিতৃপুরুষদের//পূর্বকালের","fm":"তিনি ব্যতীত কোন উপাস্য নেই। তিনি জীবন দান করেন ও মৃত্যু দেন। তিনি তোমাদের পালনকর্তা এবং তোমাদের পূর্ববর্তী পিতৃ-পুরুষদেরও পালনকর্তা।","fme":"La ilaha illa Huwa (none has the right to be worshipped but He). It is He Who gives life and causes death, your Lord and the Lord of your fore-fathers"},{"p":496,"w":"بَلْ/بَلۡ/./bal|هُمْ/هُمۡ/./hum|فِیْ/فِي/./fi|شَكٍّ/شَكّٖ/./shakkin|یَّلْعَبُوْنَ/يَلۡعَبُونَ/./yal'abuna","e":"Nay//they//(are) in//doubt //playing","m":"বরং//তারা//মধ্যে//সন্দেহের//খেলা করছে","fm":"এতদসত্ত্বেও এরা সন্দেহে পতিত হয়ে ক্রীড়া-কৌতুক করছে।","fme":"Nay! They play in doubt"},{"p":496,"w":"فَارْتَقِبْ/فَٱرۡتَقِبۡ/./fa-ir'taqib|یَوْمَ/يَوۡمَ/./yawma|تَاْتِی/تَأۡتِي/./tati|السَّمَآءُ/ٱلسَّمَآءُ/./al-samau|بِدُخَانٍ/بِدُخَانٖ/./bidukhanin|مُّبِیْنٍ/مُّبِينٖ/./mubinin","e":"Then watch//(for the) Day//(when) will bring//the sky//smoke//visible","m":"সুতরাং অপেক্ষা করো//সেই দিনের (যখন)//আসবে//আকাশ//নিয়ে ধোঁয়া (আচ্ছন্ন হয়ে)//সুস্পষ্ট","fm":"অতএব আপনি সেই দিনের অপেক্ষা করুন, যখন আকাশ ধূয়ায় ছেয়ে যাবে।","fme":"Then wait you for the Day when the sky will bring forth a visible smoke"},{"p":496,"w":"یَّغْشَی/يَغۡشَى/./yaghsha|النَّاسَ ؕ—/ٱلنَّاسَۖ/./al-nasa|هٰذَا/هَٰذَا/./hadha|عَذَابٌ/عَذَابٌ/./adhabun|اَلِیْمٌ/أَلِيمٞ/./alimun","e":"Enveloping//the people//This//(will be) a punishment//painful","m":"ঢেকে নিবে//মানুষকে//এটাই//শাস্তি//নিদারুণ","fm":"যা মানুষকে ঘিরে ফেলবে। এটা যন্ত্রণাদায়ক শাস্তি।","fme":"Covering the people, this is a painful torment"},{"p":496,"w":"رَبَّنَا/رَّبَّنَا/./rabbana|اكْشِفْ/ٱكۡشِفۡ/./ik'shif|عَنَّا/عَنَّا/./anna|الْعَذَابَ/ٱلۡعَذَابَ/./al-'adhaba|اِنَّا/إِنَّا/./inna|مُؤْمِنُوْنَ/مُؤۡمِنُونَ/./mu'minuna","e":"Our Lord!//Remove//from us//the punishment//indeed we//(are) believers","m":"\"(এখন তারা বলে) হে আমাদের রব//দূর করো//আমাদের থেকে//শাস্তি//নিশ্চয়ই আমরা//বিশ্বাসী হবো (ঈমান আনবো)\"","fm":"হে আমাদের পালনকর্তা আমাদের উপর থেকে শাস্তি প্রত্যাহার করুন, আমরা বিশ্বাস স্থাপন করছি।","fme":"(They will say): \"Our Lord! Remove the torment from us, really we shall become believers"},{"p":496,"w":"اَنّٰی/أَنَّىٰ/./anna|لَهُمُ/لَهُمُ/./lahumu|الذِّكْرٰی/ٱلذِّكۡرَىٰ/./al-dhik'ra|وَقَدْ/وَقَدۡ/./waqad|جَآءَهُمْ/جَآءَهُمۡ/./jaahum|رَسُوْلٌ/رَسُولٞ/./rasulun|مُّبِیْنٌ/مُّبِينٞ/./mubinun","e":"How can//(there be) for them//the reminder//when verily//had come to them//a Messenger//clear","m":"কেমন করে হবে//তাদের জন্যে//উপদেশ গ্রহণ (সম্ভব হবে)//অথচ নিশ্চয়ই//তাদের কাছে এসেছে//একজন রাসূল//সুস্পষ্ট","fm":"তারা কি করে বুঝবে, অথচ তাদের কাছে এসেছিলেন স্পষ্ট বর্ণনাকারী রসূল।","fme":"How can there be for them an admonition (at the time when the torment has reached them), when a Messenger explaining things clearly has already come to them"},{"p":496,"w":"ثُمَّ/ثُمَّ/./thumma|تَوَلَّوْا/تَوَلَّوۡاْ/./tawallaw|عَنْهُ/عَنۡهُ/./anhu|وَقَالُوْا/وَقَالُواْ/./waqalu|مُعَلَّمٌ/مُعَلَّمٞ/./mu'allamun|مَّجْنُوْنٌ/مَّجۡنُونٌ/./majnunun","e":"Then//they turned away//from him//and said//One taught//a mad man","m":"এরপরও//তারা ফিরে যায়//তা হ'তে//এবং তারা বললো//\"(সে একজন) প্রশিক্ষণপ্রাপ্ত//পাগল\"","fm":"অতঃপর তারা তাকে পৃষ্ঠপ্রদর্শন করে এবং বলে, সে তো উম্মাদ-শিখানো কথা বলে।","fme":"Then they had turned away from him (Messenger Muhammad SAW) and said: \"One (Muhammad SAW) taught (by a human being), a madman"},{"p":496,"w":"اِنَّا/إِنَّا/./inna|كَاشِفُوا/كَاشِفُواْ/./kashifu|الْعَذَابِ/ٱلۡعَذَابِ/./al-'adhabi|قَلِیْلًا/قَلِيلًاۚ/./qalilan|اِنَّكُمْ/إِنَّكُمۡ/./innakum|عَآىِٕدُوْنَ/عَآئِدُونَ/./aiduna","e":"Indeed We//(will) remove//the punishment//a little//indeed you//(will) return","m":"নিশ্চয়ই আমরা//দূর করে দিই//শাস্তি//কিছুটা (তবুও)//তোমরা নিশ্চয়ই//আগের অবস্হায় ফিরে যাও (যা পূর্বে করতে)","fm":"আমি তোমাদের উপর থেকে আযাব কিছুটা প্রত্যাহার করব, কিন্তু তোমরা পুনরায় পুনর্বস্থায় ফিরে যাবে।","fme":"Verily, We shall remove the torment for a while. Verily! You will revert"},{"p":496,"w":"یَوْمَ/يَوۡمَ/./yawma|نَبْطِشُ/نَبۡطِشُ/./nabtishu|الْبَطْشَةَ/ٱلۡبَطۡشَةَ/./al-batshata|الْكُبْرٰی ۚ—/ٱلۡكُبۡرَىٰٓ/./al-kub'ra|اِنَّا/إِنَّا/./inna|مُنْتَقِمُوْنَ/مُنتَقِمُونَ/./muntaqimuna","e":"(The) Day//We will seize//(with) the seizure//the greatest//indeed We//(will) take retribution","m":"যেদিন//আমরা পাকড়াও করবো//পাকড়াও//কঠিনভাবে//নিশ্চয়ই আমরা//প্রতিশোধ গ্রহণকারী(সেহদিন)","fm":"যেদিন আমি প্রবলভাবে ধৃত করব, সেদিন পুরোপুরি প্রতিশোধ গ্রহণ করবই।","fme":"On the Day when We shall seize you with the greatest grasp. Verily, We will exact retribution"},{"p":496,"w":"وَلَقَدْ/۞وَلَقَدۡ/./walaqad|فَتَنَّا/فَتَنَّا/./fatanna|قَبْلَهُمْ/قَبۡلَهُمۡ/./qablahum|قَوْمَ/قَوۡمَ/./qawma|فِرْعَوْنَ/فِرۡعَوۡنَ/./fir'awna|وَجَآءَهُمْ/وَجَآءَهُمۡ/./wajaahum|رَسُوْلٌ/رَسُولٞ/./rasulun|كَرِیْمٌ/كَرِيمٌ/./karimun","e":"And certainly//We tried//before them//(the) people//(of) Firaun//and came to them//a Messenger//noble","m":"এবং নিশ্চয়ই//আমরা পরীক্ষা করেছি//তাদের পুর্বে//জাতিকে//ফিরআউনের//এবং তাদের কাছে এসেছিলো//একজন রাসূল//মহান","fm":"তাদের পূর্বে আমি ফেরাউনের সম্প্রদায়কে পরীক্ষা করেছি এবং তাদের কাছে আগমন করেছেন একজন সম্মানিত রসূল","fme":"And indeed We tried before them Fir'aun's (Pharaoh) people, when there came to them a noble Messenger [i.e. Musa (Moses]"},{"p":496,"w":"اَنْ/أَنۡ/./an|اَدُّوْۤا/أَدُّوٓاْ/./addu|اِلَیَّ/إِلَيَّ/./ilayya|عِبَادَ/عِبَادَ/./ibada|اللّٰهِ ؕ—/ٱللَّهِۖ/./al-lahi|اِنِّیْ/إِنِّي/./inni|لَكُمْ/لَكُمۡ/./lakum|رَسُوْلٌ/رَسُولٌ/./rasulun|اَمِیْنٌ/أَمِينٞ/./aminun","e":"That//Deliver//to me//(the) servants//(of) Allah//Indeed I am//to you//a Messenger//trustworthy","m":"(সে বলেছিলো) যে//\"তোমরা সমর্পণ করো//আমার কাছে//দাসদেরকে//আল্লাহ্‌র//নিশ্চয়ই আমি//তোমাদের জন্যে//রাসূল//বিশ্বস্ত","fm":"এই মর্মে যে, আল্লাহর বান্দাদেরকে আমার কাছে অর্পণ কর। আমি তোমাদের জন্য প্রেরীত বিশ্বস্ত রসূল।","fme":"Saying: \"Restore to me the slaves of Allah (i.e. the Children of Israel). Verily! I am to you a Messenger worthy of all trust"},{"p":497,"w":"وَّاَنْ/وَأَن/./wa-an|لَّا/لَّا/./la|تَعْلُوْا/تَعۡلُواْ/./ta'lu|عَلَی/عَلَى/./ala|اللّٰهِ ؕ—/ٱللَّهِۖ/./al-lahi|اِنِّیْۤ/إِنِّيٓ/./inni|اٰتِیْكُمْ/ءَاتِيكُم/./atikum|بِسُلْطٰنٍ/بِسُلۡطَٰنٖ/./bisul'tanin|مُّبِیْنٍ/مُّبِينٖ/./mubinin","e":"And that//(do) not//exalt yourselves//against//Allah//Indeed I//[I] have come to you//with an authority//clear","m":"এবং (এও বলেছিল) যে//না//বড়াই করো//উপর//আল্লাহ্‌র//আমি নিশ্চয়ই//তোমাদের কাছে এসেছি//নিয়ে প্রমাণ//সুস্পষ্ট","fm":"আর তোমরা আল্লাহর বিরুদ্ধে ঔদ্ধত্য প্রকাশ করো না। আমি তোমাদের কাছে প্রকাশ্য প্রমাণ উপস্থিত করছি।","fme":"And exalt not (yourselves) against Allah. Truly, I have come to you with a manifest authority"},{"p":497,"w":"وَاِنِّیْ/وَإِنِّي/./wa-inni|عُذْتُ/عُذۡتُ/./udh'tu|بِرَبِّیْ/بِرَبِّي/./birabbi|وَرَبِّكُمْ/وَرَبِّكُمۡ/./warabbikum|اَنْ/أَن/./an|تَرْجُمُوْنِ/تَرۡجُمُونِ/./tarjumuni","e":"And indeed I//[I] seek refuge//with my Lord//and your Lord//lest//you stone me","m":"এবং নিশ্চয়ই আমি//আশ্রয় নিয়েছি//আমার রবের (কাছে)//এবং তোমাদের (প্রকৃত রবের)//(এ হ'তে) যে//আমাকে তোমরা পাথর মেরে হত্যা করবে","fm":"তোমরা যাতে আমাকে প্রস্তরবর্ষণে হত্যা না কর, তজ্জন্যে আমি আমার পালনকর্তা ও তোমাদের পালনকর্তার শরনাপন্ন হয়েছি।","fme":"And truly, I seek refuge in my Lord and your Lord, lest you stone me (or call me a sorcerer or kill me)"},{"p":497,"w":"وَاِنْ/وَإِن/./wa-in|لَّمْ/لَّمۡ/./lam|تُؤْمِنُوْا/تُؤۡمِنُواْ/./tu'minu|لِیْ/لِي/./li|فَاعْتَزِلُوْنِ/فَٱعۡتَزِلُونِ/./fa-i'taziluni","e":"And if//not//you believe//me//then leave me alone","m":"আর যদি//না//তোমরা ঈমান আনো//আমার উপর//তবে আমার থেকে দূরে থাকো\"","fm":"তোমরা যদি আমার প্রতি বিশ্বাস স্থাপন না কর, তবে আমার কাছ থেকে দূরে থাক।","fme":"But if you believe me not, then keep away from me and leave me alone"},{"p":497,"w":"فَدَعَا/فَدَعَا/./fada'a|رَبَّهٗۤ/رَبَّهُۥٓ/./rabbahu|اَنَّ/أَنَّ/./anna|هٰۤؤُلَآءِ/هَٰٓؤُلَآءِ/./haulai|قَوْمٌ/قَوۡمٞ/./qawmun|مُّجْرِمُوْنَ/مُّجۡرِمُونَ/./muj'rimuna","e":"So he called//his Lord//That//these//(are) a people//criminals","m":"অবশেষে সে ডাকলো//তার রবকে//\"(এবং বললো) যে//এসব//সম্প্রদায়//অপরাধী (তাদের মীমাংসা করো)\"","fm":"অতঃপর সে তার পালনকর্তার কাছে দোয়া করল যে, এরা অপরাধী সম্প্রদায়।","fme":"(But they were aggressive), so he [Musa (Moses)] called upon his Lord (saying): \"These are indeed the people who are Mujrimun (disbelievers, polytheists, sinners, criminals, etc)"},{"p":497,"w":"فَاَسْرِ/فَأَسۡرِ/./fa-asri|بِعِبَادِیْ/بِعِبَادِي/./bi'ibadi|لَیْلًا/لَيۡلًا/./laylan|اِنَّكُمْ/إِنَّكُم/./innakum|مُّتَّبَعُوْنَ/مُّتَّبَعُونَ/./muttaba'una","e":"Then Set out//with My slaves//(by) night//Indeed you//(will be) followed","m":"(বলা হলো) রওনা হও তাহ'লে//আমার দাসদের নিয়ে//রাতে//নিশ্চয়ই তোমাদের//পিছনে (ধাওয়া) করা হবে","fm":"তাহলে তুমি আমার বান্দাদেরকে নিয়ে রাত্রিবেলায় বের হয়ে পড়। নিশ্চয় তোমাদের পশ্চাদ্ধবন করা হবে।","fme":"(Allah said): \"Depart you with My slaves by night. Surely, you will be pursued"},{"p":497,"w":"وَاتْرُكِ/وَٱتۡرُكِ/./wa-ut'ruki|الْبَحْرَ/ٱلۡبَحۡرَ/./al-bahra|رَهْوًا ؕ—/رَهۡوًاۖ/./rahwan|اِنَّهُمْ/إِنَّهُمۡ/./innahum|جُنْدٌ/جُندٞ/./jundun|مُّغْرَقُوْنَ/مُّغۡرَقُونَ/./mugh'raquna","e":"And leave//the sea//at rest//Indeed they//(are) an army//(to be) drowned","m":"এবং ছেড়ে দাও//সাগরকে//শান্ত অবস্হায়//তারা নিশ্চয়ই//(অর্থাৎ ধাওয়াকারী) সৈন্যবাহিনী//ডুবে যাবে\"","fm":"এবং সমুদ্রকে অচল থাকতে দাও। নিশ্চয় ওরা নিমজ্জত বাহিনী।","fme":"And leave the sea as it is (quiet and divided). Verily, They are a host to be drowned"},{"p":497,"w":"كَمْ/كَمۡ/./kam|تَرَكُوْا/تَرَكُواْ/./taraku|مِنْ/مِن/./min|جَنّٰتٍ/جَنَّٰتٖ/./jannatin|وَّعُیُوْنٍ/وَعُيُونٖ/./wa'uyunin","e":"How many//(did) they leave//of//gardens//and springs","m":"কতই না//তারা ছেড়েছিলো//মধ্য হতে//বাগান//ও ঝর্ণাসমূহ","fm":"তারা ছেড়ে গিয়েছিল কত উদ্যান ও প্রস্রবন","fme":"How many of gardens and springs do they [Fir'aun's (Pharaoh) people] left"},{"p":497,"w":"وَّزُرُوْعٍ/وَزُرُوعٖ/./wazuru'in|وَّمَقَامٍ/وَمَقَامٖ/./wamaqamin|كَرِیْمٍ/كَرِيمٖ/./karimin","e":"And cornfields//and places//noble","m":"এবং শস্যক্ষেত//ও বাসস্থান//সুন্দর","fm":"কত শস্যক্ষেত্র ও সূরম্য স্থান।","fme":"And green crops (fields etc.) and goodly places"},{"p":497,"w":"وَّنَعْمَةٍ/وَنَعۡمَةٖ/./wana'matin|كَانُوْا/كَانُواْ/./kanu|فِیْهَا/فِيهَا/./fiha|فٰكِهِیْنَ/فَٰكِهِينَ/./fakihina","e":"And pleasant things//they used to//therein//take delight!","m":"এবং বিলাস//তারা ছিলো//যার মধ্যে//আনন্দকারী (সব ছেড়ে চলে গেলো)","fm":"কত সুখের উপকরণ, যাতে তারা খোশগল্প করত।","fme":"And comforts of life wherein they used to take delight"},{"p":497,"w":"كَذٰلِكَ ۫—/كَذَٰلِكَۖ/./kadhalika|وَاَوْرَثْنٰهَا/وَأَوۡرَثۡنَٰهَا/./wa-awrathnaha|قَوْمًا/قَوۡمًا/./qawman|اٰخَرِیْنَ/ءَاخَرِينَ/./akharina","e":"Thus//And We made it (an) inherit(ance)//(for) a people//another","m":"এভাবেই (পরিণাম হয়েছিলো)//এবং তার আমরা উত্তরাধিকারী করেছিলাম//সম্প্রদায়কে//অন্য","fm":"এমনিই হয়েছিল এবং আমি ওগুলোর মালিক করেছিলাম ভিন্ন সম্প্রদায়কে।","fme":"Thus (it was)! And We made other people inherit them (i.e. We made the Children of Israel to inherit the kingdom of Egypt)"},{"p":497,"w":"فَمَا/فَمَا/./fama|بَكَتْ/بَكَتۡ/./bakat|عَلَیْهِمُ/عَلَيۡهِمُ/./alayhimu|السَّمَآءُ/ٱلسَّمَآءُ/./al-samau|وَالْاَرْضُ/وَٱلۡأَرۡضُ/./wal-ardu|وَمَا/وَمَا/./wama|كَانُوْا/كَانُواْ/./kanu|مُنْظَرِیْنَ/مُنظَرِينَ/./munzarina","e":"And not//wept//for them//the heaven//and the earth//and not//they were//given respite","m":"না অতঃপর//কাঁদলো//তাদের উপর//আকাশ//আর (না) পৃথিবী//এবং না//তারা ছিলো//অবকাশপ্রাপ্ত","fm":"তাদের জন্যে ক্রন্দন করেনি আকাশ ও পৃথিবী এবং তারা অবকাশও পায়নি।","fme":"And the heavens and the earth wept not for them, nor were they given a respite"},{"p":497,"w":"وَلَقَدْ/وَلَقَدۡ/./walaqad|نَجَّیْنَا/نَجَّيۡنَا/./najjayna|بَنِیْۤ/بَنِيٓ/./bani|اِسْرَآءِیْلَ/إِسۡرَٰٓءِيلَ/./is'raila|مِنَ/مِنَ/./mina|الْعَذَابِ/ٱلۡعَذَابِ/./al-'adhabi|الْمُهِیْنِ/ٱلۡمُهِينِ/./al-muhini","e":"And certainly//We saved//(the) Children of Israel//(the) Children of Israel//from//the punishment//the humiliating","m":"এবং নিশ্চয়ই//আমরা উদ্ধার করেছিলাম//বনী//ইসরাঈলকে//থেকে//শাস্তি//অপমানজনক","fm":"আমি বনী-ইসরাঈলকে অপমানজনক শাস্তি থেকে উদ্ধার করছি।","fme":"And indeed We saved the Children of Israel from the humiliating torment"},{"p":497,"w":"مِنْ/مِن/./min|فِرْعَوْنَ ؕ—/فِرۡعَوۡنَۚ/./fir'awna|اِنَّهٗ/إِنَّهُۥ/./innahu|كَانَ/كَانَ/./kana|عَالِیًا/عَالِيٗا/./aliyan|مِّنَ/مِّنَ/./mina|الْمُسْرِفِیْنَ/ٱلۡمُسۡرِفِينَ/./al-mus'rifina","e":"From//Firaun//Indeed he//was//arrogant//among//the transgressors","m":"দেওয়া//ফিরআউনের//সে নিশ্চয়ই//ছিলো//পরাক্রান্ত//মধ্য হতে//সীমালংঘনকারীদের","fm":"ফেরাউন সে ছিল সীমালংঘনকারীদের মধ্যে শীর্ষস্থানীয়।","fme":"From Fir'aun (Pharaoh); Verily! He was arrogant and was of the Musrifun (those who transgress beyond bound in spending and other things and commit great sins)"},{"p":497,"w":"وَلَقَدِ/وَلَقَدِ/./walaqadi|اخْتَرْنٰهُمْ/ٱخۡتَرۡنَٰهُمۡ/./ikh'tarnahum|عَلٰی/عَلَىٰ/./ala|عِلْمٍ/عِلۡمٍ/./il'min|عَلَی/عَلَى/./ala|الْعٰلَمِیْنَ/ٱلۡعَٰلَمِينَ/./al-'alamina","e":"And certainly//We chose them//by//knowledge//over//the worlds","m":"এবং নিশ্চয়ই//তাদেরকে (বনী ইসরাঈলকে) আমরা মনোনীত করেছিলাম//ভিত্তিতে//জ্ঞানের//উপর//বিশ্ববাসীর (অন্যান্য জাতির)","fm":"আমি জেনেশুনে তাদেরকে বিশ্ববাসীদের উপর শ্রেষ্ঠত্ব দিয়েছিলাম।","fme":"And We chose them (the Children of Israel) above the 'Alamin (mankind, and jinns) [during the time of Musa (Moses)] with knowledge"},{"p":497,"w":"وَاٰتَیْنٰهُمْ/وَءَاتَيۡنَٰهُم/./waataynahum|مِّنَ/مِّنَ/./mina|الْاٰیٰتِ/ٱلۡأٓيَٰتِ/./al-ayati|مَا/مَا/./ma|فِیْهِ/فِيهِ/./fihi|بَلٰٓؤٌا/بَلَٰٓؤٞاْ/./balaon|مُّبِیْنٌ/مُّبِينٌ/./mubinun","e":"And We gave them//of//the Signs//that//in it//(was) a trial//clear","m":"এবং তাদেরকে আমরা দিয়েছিলাম//কিছু//নিদর্শনাবলী//যার//মধ্যে ছিলো//পরীক্ষা//সুস্পষ্ট","fm":"এবং আমি তাদেরকে এমন নিদর্শনাবলী দিয়েছিলাম যাতে ছিল স্পষ্ট সাহায্য।","fme":"And granted them signs in which there was a plain trial"},{"p":497,"w":"اِنَّ/إِنَّ/./inna|هٰۤؤُلَآءِ/هَٰٓؤُلَآءِ/./haulai|لَیَقُوْلُوْنَ/لَيَقُولُونَ/./layaquluna","e":"Indeed//these//surely they say","m":"নিশ্চয়ই//এসব লোক//অবশ্যই বলে","fm":"কাফেররা বলেই থাকে","fme":"Verily, these (Quraish) people are saying"},{"p":497,"w":"اِنْ/إِنۡ/./in|هِیَ/هِيَ/./hiya|اِلَّا/إِلَّا/./illa|مَوْتَتُنَا/مَوۡتَتُنَا/./mawtatuna|الْاُوْلٰی/ٱلۡأُولَىٰ/./al-ula|وَمَا/وَمَا/./wama|نَحْنُ/نَحۡنُ/./nahnu|بِمُنْشَرِیْنَ/بِمُنشَرِينَ/./bimunsharina","e":"Not//it//(is) but//our death//the first//and not//we//(will be) raised again","m":"\"নেই//তা//এ ব্যতীত//আমাদের মৃত্যু//প্রথম (অর্থাৎ মৃতই শেষ)//এবং না//আমরা//উত্থিত হবো","fm":"প্রথম মৃত্যুর মাধ্যমেই আমাদের সবকিছুর অবসান হবে এবং আমরা পুনরুত্থিত হব না।","fme":"There is nothing but our first death, and we shall not be resurrected"},{"p":497,"w":"فَاْتُوْا/فَأۡتُواْ/./fatu|بِاٰبَآىِٕنَاۤ/بِـَٔابَآئِنَآ/./biabaina|اِنْ/إِن/./in|كُنْتُمْ/كُنتُمۡ/./kuntum|صٰدِقِیْنَ/صَٰدِقِينَ/./sadiqina","e":"Then bring//our forefathers//if//you are//truthful","m":"তোমরা তবে আসো//নিয়ে আমাদের পিতৃপুরুষদেরকে//যদি//তোমরা হও//সত্যবাদী\"","fm":"তোমরা যদি সত্যবাদী হও, তবে আমাদের পূর্বপুরুষদেরকে নিয়ে এস।","fme":"Then bring back our fore-fathers, if you speak the truth"},{"p":497,"w":"اَهُمْ/أَهُمۡ/./ahum|خَیْرٌ/خَيۡرٌ/./khayrun|اَمْ/أَمۡ/./am|قَوْمُ/قَوۡمُ/./qawmu|تُبَّعٍ ۙ—/تُبَّعٖ/./tubba'in|وَّالَّذِیْنَ/وَٱلَّذِينَ/./wa-alladhina|مِنْ/مِن/./min|قَبْلِهِمْ ؕ—/قَبۡلِهِمۡ/./qablihim|اَهْلَكْنٰهُمْ ؗ—/أَهۡلَكۡنَٰهُمۡۚ/./ahlaknahum|اِنَّهُمْ/إِنَّهُمۡ/./innahum|كَانُوْا/كَانُواْ/./kanu|مُجْرِمِیْنَ/مُجۡرِمِينَ/./muj'rimina","e":"Are they//better//or//(the) people//(of) Tubba//and those//before them?//before them?//We destroyed them//indeed they//were//criminals","m":"(তাদেরকে বলো) তারা কি//উত্তম//অথবা//জাতি//তুব্বার//এবং যারা (ছিলো)//মধ্য হতে//তাদের পূর্বে//তাদেরকে আমরা ধ্বংস করেছি//তারা নিশ্চয়ই//ছিলো//অপরাধী","fm":"ওরা শ্রেষ্ঠ, না তুব্বার সম্প্রদায় ও তাদের পূর্ববর্তীরা? আমি ওদেরকে ধ্বংস করে দিয়েছি। ওরা ছিল অপরাধী।","fme":"Are they better or the people of Tubba' and those before them? We destroyed them because they were indeed Mujrimun (disbelievers, polytheists, sinners, criminals, etc)"},{"p":497,"w":"وَمَا/وَمَا/./wama|خَلَقْنَا/خَلَقۡنَا/./khalaqna|السَّمٰوٰتِ/ٱلسَّمَٰوَٰتِ/./al-samawati|وَالْاَرْضَ/وَٱلۡأَرۡضَ/./wal-arda|وَمَا/وَمَا/./wama|بَیْنَهُمَا/بَيۡنَهُمَا/./baynahuma|لٰعِبِیْنَ/لَٰعِبِينَ/./la'ibina","e":"And not//We created//the heavens//and the earth//and whatever//(is) between them//(in) play","m":"এবং না//আমরা সৃষ্টি করেছি//আকাশকে//ও পৃথিবীকে//এবং যা কিছু//উভয়ের মাঝে আছে//খেলাচ্ছলে","fm":"আমি নভোমন্ডল, ভূমন্ডল ও এতদুভয়ের মধ্যবর্তী সবকিছু ক্রীড়াচ্ছলে সৃষ্টি করিনি।","fme":"And We created not the heavens and the earth, and all that is between them, for mere play"},{"p":497,"w":"مَا/مَا/./ma|خَلَقْنٰهُمَاۤ/خَلَقۡنَٰهُمَآ/./khalaqnahuma|اِلَّا/إِلَّا/./illa|بِالْحَقِّ/بِٱلۡحَقِّ/./bil-haqi|وَلٰكِنَّ/وَلَٰكِنَّ/./walakinna|اَكْثَرَهُمْ/أَكۡثَرَهُمۡ/./aktharahum|لَا/لَا/./la|یَعْلَمُوْنَ/يَعۡلَمُونَ/./ya'lamuna","e":"Not//We created both of them//but//in [the] truth//but//most of them//(do) not//know","m":"না//উভয়কে আমরা সৃষ্টি করেছি//এ ব্যতীত//সত্যসহ//কিন্তু//তাদের অধিকাংশই//না//জানে","fm":"আমি এগুলো যথাযথ উদ্দেশ্যে সৃষ্টি করেছি; কিন্তু তাদের অধিকাংশই বোঝে না।","fme":"We created them not except with truth (i.e. to examine and test those who are obedient and those who are disobedient and then reward the obedient ones and punish the disobedient ones), but most of them know not"},{"p":498,"w":"اِنَّ/إِنَّ/./inna|یَوْمَ/يَوۡمَ/./yawma|الْفَصْلِ/ٱلۡفَصۡلِ/./al-fasli|مِیْقَاتُهُمْ/مِيقَٰتُهُمۡ/./miqatuhum|اَجْمَعِیْنَ/أَجۡمَعِينَ/./ajma'ina","e":"Indeed//(the) Day of Judgment//(the) Day of Judgment//(is) an appointed term for them//all","m":"নিশ্চয়ই (আসবে)//দিন//মীমাংসার//তাদের নির্ধারিত সময়ে//সকলেরই","fm":"নিশ্চয় ফয়সালার দিন তাদের সবারই নির্ধারিত সময়।","fme":"Verily, the Day of Judgement (when Allah will judge between the creatures) is the time appointed for all of them"},{"p":498,"w":"یَوْمَ/يَوۡمَ/./yawma|لَا/لَا/./la|یُغْنِیْ/يُغۡنِي/./yugh'ni|مَوْلًی/مَوۡلًى/./mawlan|عَنْ/عَن/./an|مَّوْلًی/مَّوۡلٗى/./mawlan|شَیْـًٔا/شَيۡـٔٗا/./shayan|وَّلَا/وَلَا/./wala|هُمْ/هُمۡ/./hum|یُنْصَرُوْنَ/يُنصَرُونَ/./yunsaruna","e":"(The) Day//not//will avail//a relation//for//a relation//anything//and not//they//will be helped","m":"যেদিন//না//কাজে লাগবে//কোনো বন্ধু//জন্যে//(অপর) কোনো বন্ধুর//কিছুমাত্র//আর না//তাদের//সাহায্য করা হবে","fm":"যেদিন কোন বন্ধুই কোন বন্ধুর উপকারে আসবে না এবং তারা সাহায্যপ্রাপ্তও হবে না।","fme":"The Day when Maulan (a near relative) cannot avail Maulan (a near relative) in aught, and no help can they receive"},{"p":498,"w":"اِلَّا/إِلَّا/./illa|مَنْ/مَن/./man|رَّحِمَ/رَّحِمَ/./rahima|اللّٰهُ ؕ—/ٱللَّهُۚ/./al-lahu|اِنَّهٗ/إِنَّهُۥ/./innahu|هُوَ/هُوَ/./huwa|الْعَزِیْزُ/ٱلۡعَزِيزُ/./al-'azizu|الرَّحِیْمُ/ٱلرَّحِيمُ/./al-rahimu","e":"Except//(on) whom//Allah has mercy//Allah has mercy//Indeed He//[He]//(is) the AllMighty//the Most Merciful","m":"কিন্তু//যাকে//দয়া করবেন//আল্লাহ (সেটা অন্য কথা)//তিনি নিশ্চয়ই//তিনিই//পরাক্রমশালী//দয়ালু","fm":"তবে আল্লাহ যার প্রতি দয়া করেন, তার কথা ভিন্ন। নিশ্চয় তিনি পরাক্রমশালী দয়াময়।","fme":"Except him on whom Allah has Mercy. Verily, He is the All-Mighty, the Most Merciful"},{"p":498,"w":"اِنَّ/إِنَّ/./inna|شَجَرَتَ/شَجَرَتَ/./shajarata|الزَّقُّوْمِ/ٱلزَّقُّومِ/./al-zaqumi","e":"Indeed//(the) tree//(of) Zaqqum","m":"নিশ্চয়ই//গাছ//যাক্কুম'","fm":"নিশ্চয় যাক্কুম বৃক্ষ","fme":"Verily, the tree of Zaqqum"},{"p":498,"w":"طَعَامُ/طَعَامُ/./ta'amu|الْاَثِیْمِ/ٱلۡأَثِيمِ/./al-athimi","e":"(Will be) food//(of) the sinner(s)","m":"খাদ্য//পাপীদের","fm":"পাপীর খাদ্য হবে","fme":"Will be the food of the sinners"},{"p":498,"w":"كَالْمُهْلِ ۛۚ—/كَٱلۡمُهۡلِ/./kal-muh'li|یَغْلِیْ/يَغۡلِي/./yaghli|فِی/فِي/./fi|الْبُطُوْنِ/ٱلۡبُطُونِ/./al-butuni","e":"Like the murky oil//it will boil//in//the bellies","m":"গলিত তামার মতো//ফুটবে//মধ্যে//পেটের","fm":"গলিত তাম্রের মত পেটে ফুটতে থাকবে।","fme":"Like boiling oil, it will boil in the bellies"},{"p":498,"w":"كَغَلْیِ/كَغَلۡيِ/./kaghalyi|الْحَمِیْمِ/ٱلۡحَمِيمِ/./al-hamimi","e":"Like boiling//(of) scalding water","m":"ফুটে যেমন//ফুটন্ত পানি","fm":"যেমন ফুটে পানি।","fme":"Like the boiling of scalding water"},{"p":498,"w":"خُذُوْهُ/خُذُوهُ/./khudhuhu|فَاعْتِلُوْهُ/فَٱعۡتِلُوهُ/./fa-i'tiluhu|اِلٰی/إِلَىٰ/./ila|سَوَآءِ/سَوَآءِ/./sawai|الْجَحِیْمِ/ٱلۡجَحِيمِ/./al-jahimi","e":"Seize him//and drag him//into//(the) midst//(of) the Hellfire","m":"\"(বলা হবে) তাকে ধরো//এরপর তাকে টেনে নাও//দিকে//মধ্যস্থলে//জাহান্নামের","fm":"একে ধর এবং টেনে নিয়ে যাও জাহান্নামের মধ্যস্থলে","fme":"(It will be said) \"Seize him and drag him into the midst of blazing Fire"},{"p":498,"w":"ثُمَّ/ثُمَّ/./thumma|صُبُّوْا/صُبُّواْ/./subbu|فَوْقَ/فَوۡقَ/./fawqa|رَاْسِهٖ/رَأۡسِهِۦ/./rasihi|مِنْ/مِنۡ/./min|عَذَابِ/عَذَابِ/./adhabi|الْحَمِیْمِ/ٱلۡحَمِيمِ/./al-hamimi","e":"Then//pour//over//his head//of//(the) punishment//(of) the scalding water","m":"এরপর//তোমরা ঢালো//উপর//তার মাথায়//থেকে//শাস্তি//ফুটন্ত পানির","fm":"অতঃপর তার মাথার উপর ফুটন্ত পানির আযাব ঢেলে দাও","fme":"Then pour over his head the torment of boiling water"},{"p":498,"w":"ذُقْ ۖۚ—/ذُقۡ/./dhuq|اِنَّكَ/إِنَّكَ/./innaka|اَنْتَ/أَنتَ/./anta|الْعَزِیْزُ/ٱلۡعَزِيزُ/./al-'azizu|الْكَرِیْمُ/ٱلۡكَرِيمُ/./al-karimu","e":"Taste!//Indeed you//[you] (were)//the mighty//the noble","m":"(বলা হবে) স্বাদ নাও//তুমি নিশ্চয়ই//তুমিই (ছিলে)//পরাক্রমশালী(?)//সম্মানিত","fm":"স্বাদ গ্রহণ কর, তুমি তো সম্মানিত, সম্ভ্রান্ত।","fme":"Taste you (this)! Verily, you were (pretending to be) the mighty, the generous"},{"p":498,"w":"اِنَّ/إِنَّ/./inna|هٰذَا/هَٰذَا/./hadha|مَا/مَا/./ma|كُنْتُمْ/كُنتُم/./kuntum|بِهٖ/بِهِۦ/./bihi|تَمْتَرُوْنَ/تَمۡتَرُونَ/./tamtaruna","e":"Indeed//this//(is) what//you used to//[about it]//doubt","m":"নিশ্চয়ই//এটাই//(সেই জিনিষ) যা//তোমরা ছিলে//সে সম্বন্ধে//সন্দেহ করতে\"","fm":"এ সম্পর্কে তোমরা সন্দেহে পতিত ছিলে।","fme":"Verily! This is that whereof you used to doubt"},{"p":498,"w":"اِنَّ/إِنَّ/./inna|الْمُتَّقِیْنَ/ٱلۡمُتَّقِينَ/./al-mutaqina|فِیْ/فِي/./fi|مَقَامٍ/مَقَامٍ/./maqamin|اَمِیْنٍ/أَمِينٖ/./aminin","e":"Indeed//the righteous//(will be) in//a place//secure","m":"নিশ্চয়ই//মুত্তাকীরা (থাকবে)//মধ্যে//স্থানের//নিরাপদ","fm":"নিশ্চয় খোদাভীরুরা নিরাপদ স্থানে থাকবে","fme":"Verily! The Muttaqun (pious - see V. 2:2), will be in place of Security (Paradise)"},{"p":498,"w":"فِیْ/فِي/./fi|جَنّٰتٍ/جَنَّٰتٖ/./jannatin|وَّعُیُوْنٍ/وَعُيُونٖ/./wa'uyunin","e":"In//gardens//and springs","m":"মধ্যে//বাগানের//ও ঝর্ণাসমূহের","fm":"উদ্যানরাজি ও নির্ঝরিণীসমূহে।","fme":"Among Gardens and Springs"},{"p":498,"w":"یَّلْبَسُوْنَ/يَلۡبَسُونَ/./yalbasuna|مِنْ/مِن/./min|سُنْدُسٍ/سُندُسٖ/./sundusin|وَّاِسْتَبْرَقٍ/وَإِسۡتَبۡرَقٖ/./wa-is'tabraqin|مُّتَقٰبِلِیْنَ/مُّتَقَٰبِلِينَ/./mutaqabilina","e":"Wearing garments//of//fine silk//and heavy silk//facing each other","m":"তারা পোশাক পরবে//তৈরী//মিহি রেশমের//ও পুরু রেশমের//মুখোমুখী (হয়ে বসবে)","fm":"তারা পরিধান করবে চিকন ও পুরু রেশমীবস্ত্র, মুখোমুখি হয়ে বসবে।","fme":"Dressed in fine silk and (also) in thick silk, facing each other"},{"p":498,"w":"كَذٰلِكَ ۫—/كَذَٰلِكَ/./kadhalika|وَزَوَّجْنٰهُمْ/وَزَوَّجۡنَٰهُم/./wazawwajnahum|بِحُوْرٍ/بِحُورٍ/./bihurin|عِیْنٍ/عِينٖ/./inin","e":"Thus//And We will marry them//(to) companions with beautiful eyes//(to) companions with beautiful eyes","m":"এভাবেই (ঘটবে)//এবং তাদের আমরা  বিয়ে দিবো//(সুন্দরী-রূপসী) সাথে হুরদের//আয়তলোচনা (হরিণ-নয়না)","fm":"এরূপই হবে এবং আমি তাদেরকে আনতলোচনা স্ত্রী দেব।","fme":"So (it will be), and We shall marry them to Houris (female fair ones) with wide, lovely eyes"},{"p":498,"w":"یَدْعُوْنَ/يَدۡعُونَ/./yad'una|فِیْهَا/فِيهَا/./fiha|بِكُلِّ/بِكُلِّ/./bikulli|فَاكِهَةٍ/فَٰكِهَةٍ/./fakihatin|اٰمِنِیْنَ/ءَامِنِينَ/./aminina","e":"They will call//therein//for every (kind)//(of) fruit//secure","m":"তারা চেয়ে চেয়ে নিবে//তার মধ্যে//প্রত্যেক প্রকার//ফলমূল//প্রশান্ত মনে","fm":"তারা সেখানে শান্ত মনে বিভিন্ন ফল-মূল আনতে বলবে।","fme":"They will call therein for every kind of fruit in peace and security"},{"p":498,"w":"لَا/لَا/./la|یَذُوْقُوْنَ/يَذُوقُونَ/./yadhuquna|فِیْهَا/فِيهَا/./fiha|الْمَوْتَ/ٱلۡمَوۡتَ/./al-mawta|اِلَّا/إِلَّا/./illa|الْمَوْتَةَ/ٱلۡمَوۡتَةَ/./al-mawtata|الْاُوْلٰی ۚ—/ٱلۡأُولَىٰۖ/./al-ula|وَوَقٰىهُمْ/وَوَقَىٰهُمۡ/./wawaqahum|عَذَابَ/عَذَابَ/./adhaba|الْجَحِیْمِ/ٱلۡجَحِيمِ/./al-jahimi","e":"Not//they will taste//therein//the death//except//the death//the first//And He will protect them//(from the) punishment//(of) the Hellfire","m":"না//তারা স্বাদ গ্রহণ করবে//তার মধ্যে//মৃত্যুর//ব্যতীত//মৃত্যু//প্রথম//এবং তাদের তিনি রক্ষা করবেন//শাস্তি (হ'তে)//জাহান্নামের","fm":"তারা সেখানে মৃত্যু আস্বাদন করবে না, প্রথম মৃত্যু ব্যতীত এবং আপনার পালনকর্তা তাদেরকে জাহান্নামের আযাব থেকে রক্ষা করবেন।","fme":"They will never taste death therein except the first death (of this world), and He will save them from the torment of the blazing Fire"},{"p":498,"w":"فَضْلًا/فَضۡلٗا/./fadlan|مِّنْ/مِّن/./min|رَّبِّكَ ؕ—/رَّبِّكَۚ/./rabbika|ذٰلِكَ/ذَٰلِكَ/./dhalika|هُوَ/هُوَ/./huwa|الْفَوْزُ/ٱلۡفَوۡزُ/./al-fawzu|الْعَظِیْمُ/ٱلۡعَظِيمُ/./al-'azimu","e":"A Bounty//from//your Lord//That //it//(will be) the success//the great","m":"অনুগ্রহে//পক্ষ হ'তে//তোমার রবের//এটাই//সেই//সাফল্য//মহা","fm":"আপনার পালনকর্তার কৃপায় এটাই মহা সাফল্য।","fme":"As a Bounty from your Lord! That will be the supreme success"},{"p":498,"w":"فَاِنَّمَا/فَإِنَّمَا/./fa-innama|یَسَّرْنٰهُ/يَسَّرۡنَٰهُ/./yassarnahu|بِلِسَانِكَ/بِلِسَانِكَ/./bilisanika|لَعَلَّهُمْ/لَعَلَّهُمۡ/./la'allahum|یَتَذَكَّرُوْنَ/يَتَذَكَّرُونَ/./yatadhakkaruna","e":"Indeed//We have made it easy//in your tongue//so that they may//take heed","m":"(হে নাবী) মূলতঃ//তা (অর্থাৎ এ কিতাবকে) আমরা সহজ করে দিয়েছি//তোমার ভাষায়//তারা যেন//উপদেশ গ্রহণ করে","fm":"আমি আপনার ভাষায় কোরআনকে সহজ করে দিয়েছি, যাতে তারা স্মরণ রাখে।","fme":"Certainly, We have made this (Quran) easy in your tongue, in order that they may remember"},{"p":498,"w":"فَارْتَقِبْ/فَٱرۡتَقِبۡ/./fa-ir'taqib|اِنَّهُمْ/إِنَّهُم/./innahum|مُّرْتَقِبُوْنَ/مُّرۡتَقِبُونَ/./mur'taqibuna","e":"So watch//indeed they//(too are) watching","m":"সুতরাং অপেক্ষা করো তুমি//তারা নিশ্চয়ই//অপেক্ষামান","fm":"অতএব, আপনি অপেক্ষা করুন, তারাও অপেক্ষা করছে।","fme":"Wait then (O Muhammad SAW); Verily, they (too) are waiting"}]